eulexistdb/__init__.py
eulexistdb/db.py
eulexistdb/debug_panel.py
eulexistdb/exceptions.py
eulexistdb/manager.py
eulexistdb/models.py
eulexistdb/patch.py
eulexistdb/query.py
eulexistdb/testutil.py
eulexistdb/management/__init__.py
eulexistdb/management/commands/__init__.py
eulexistdb/management/commands/existdb.py
eulexistdb/templates/eulexistdb/debug_panel.html
eulexistdb/templatetags/__init__.py
eulexistdb/templatetags/existdb.py
eulexistdb-0.21.1.dist-info/DESCRIPTION.rst
eulexistdb-0.21.1.dist-info/METADATA
eulexistdb-0.21.1.dist-info/metadata.json
eulexistdb-0.21.1.dist-info/RECORD
eulexistdb-0.21.1.dist-info/top_level.txt
eulexistdb-0.21.1.dist-info/WHEEL
