Metadata-Version: 2.0
Name: eulexistdb
Version: 0.21.1
Summary: Idiomatic access to the eXist-db XML Database using XPath and XQuery
Home-page: https://github.com/emory-libraries/eulexistdb
Author: Emory University Libraries
Author-email: libsysdev-l@listserv.cc.emory.edu
License: Apache License, Version 2.0
Keywords: eXist-db XQuery
Platform: UNKNOWN
Classifier: Development Status :: 4 - Beta
Classifier: Framework :: Django
Classifier: Intended Audience :: Developers
Classifier: License :: OSI Approved :: Apache Software License
Classifier: Natural Language :: English
Classifier: Operating System :: OS Independent
Classifier: Programming Language :: Python
Classifier: Topic :: Software Development :: Libraries :: Python Modules
Classifier: Topic :: Text Processing :: Markup :: XML
Requires-Dist: requests
Requires-Dist: eulxml (>=1.1.2)
Provides-Extra: dev
Requires-Dist: sphinx; extra == 'dev'
Requires-Dist: nose; extra == 'dev'
Requires-Dist: coverage; extra == 'dev'
Requires-Dist: tox; extra == 'dev'
Requires-Dist: mock; extra == 'dev'
Requires-Dist: Django; extra == 'dev'
Requires-Dist: django-debug-toolbar; extra == 'dev'
Provides-Extra: django
Requires-Dist: Django; extra == 'django'
Provides-Extra: test
Requires-Dist: sphinx; extra == 'test'
Requires-Dist: nose; extra == 'test'
Requires-Dist: coverage; extra == 'test'
Requires-Dist: tox; extra == 'test'
Requires-Dist: mock; extra == 'test'
